{
  "_comment": "BNSS Schedule I — Offence classification table. Keys: act_code → section_number → {is_cognizable, is_bailable, triable_by}. Manually extracted from BNSS.pdf Schedule I, Chapter 1. triable_by values: 'Court of Sessions', 'Magistrate First Class', 'Magistrate Second Class', 'Any Magistrate'. Populate this file before running Phase 2B classification.",
  "BNS_2023": {
    "100": { "is_cognizable": true,  "is_bailable": false, "triable_by": "Court of Sessions" },
    "101": { "is_cognizable": true,  "is_bailable": false, "triable_by": "Court of Sessions" },
    "103": { "is_cognizable": true,  "is_bailable": false, "triable_by": "Court of Sessions" },
    "104": { "is_cognizable": true,  "is_bailable": false, "triable_by": "Court of Sessions" },
    "105": { "is_cognizable": true,  "is_bailable": false, "triable_by": "Court of Sessions" },
    "106": { "is_cognizable": true,  "is_bailable": false, "triable_by": "Magistrate First Class" },
    "107": { "is_cognizable": true,  "is_bailable": false, "triable_by": "Magistrate First Class" },
    "109": { "is_cognizable": true,  "is_bailable": false, "triable_by": "Magistrate First Class" },
    "110": { "is_cognizable": true,  "is_bailable": false, "triable_by": "Magistrate First Class" },
    "111": { "is_cognizable": true,  "is_bailable": false, "triable_by": "Court of Sessions" },
    "112": { "is_cognizable": true,  "is_bailable": false, "triable_by": "Magistrate First Class" },
    "113": { "is_cognizable": true,  "is_bailable": false, "triable_by": "Court of Sessions" },
    "114": { "is_cognizable": true,  "is_bailable": true,  "triable_by": "Any Magistrate" },
    "115": { "is_cognizable": false, "is_bailable": true,  "triable_by": "Any Magistrate" },
    "116": { "is_cognizable": true,  "is_bailable": true,  "triable_by": "Any Magistrate" },
    "117": { "is_cognizable": false, "is_bailable": true,  "triable_by": "Any Magistrate" },
    "118": { "is_cognizable": true,  "is_bailable": false, "triable_by": "Court of Sessions" },
    "119": { "is_cognizable": true,  "is_bailable": false, "triable_by": "Court of Sessions" },
    "120": { "is_cognizable": true,  "is_bailable": false, "triable_by": "Court of Sessions" },
    "121": { "is_cognizable": true,  "is_bailable": false, "triable_by": "Magistrate First Class" },
    "125": { "is_cognizable": true,  "is_bailable": false, "triable_by": "Magistrate First Class" },
    "126": { "is_cognizable": true,  "is_bailable": false, "triable_by": "Magistrate First Class" },
    "127": { "is_cognizable": true,  "is_bailable": false, "triable_by": "Magistrate First Class" },
    "129": { "is_cognizable": true,  "is_bailable": true,  "triable_by": "Any Magistrate" },
    "130": { "is_cognizable": true,  "is_bailable": true,  "triable_by": "Any Magistrate" },
    "131": { "is_cognizable": true,  "is_bailable": true,  "triable_by": "Any Magistrate" },
    "132": { "is_cognizable": false, "is_bailable": true,  "triable_by": "Any Magistrate" },
    "140": { "is_cognizable": true,  "is_bailable": false, "triable_by": "Court of Sessions" },
    "143": { "is_cognizable": true,  "is_bailable": false, "triable_by": "Court of Sessions" },
    "152": { "is_cognizable": true,  "is_bailable": false, "triable_by": "Court of Sessions" },
    "157": { "is_cognizable": true,  "is_bailable": false, "triable_by": "Court of Sessions" },
    "158": { "is_cognizable": true,  "is_bailable": false, "triable_by": "Court of Sessions" },
    "176": { "is_cognizable": true,  "is_bailable": false, "triable_by": "Magistrate First Class" },
    "190": { "is_cognizable": true,  "is_bailable": true,  "triable_by": "Magistrate First Class" },
    "191": { "is_cognizable": true,  "is_bailable": false, "triable_by": "Court of Sessions" },
    "199": { "is_cognizable": false, "is_bailable": true,  "triable_by": "Any Magistrate" },
    "200": { "is_cognizable": false, "is_bailable": true,  "triable_by": "Any Magistrate" },
    "215": { "is_cognizable": false, "is_bailable": true,  "triable_by": "Any Magistrate" },
    "232": { "is_cognizable": true,  "is_bailable": false, "triable_by": "Court of Sessions" },
    "235": { "is_cognizable": true,  "is_bailable": false, "triable_by": "Court of Sessions" },
    "238": { "is_cognizable": true,  "is_bailable": false, "triable_by": "Court of Sessions" },
    "248": { "is_cognizable": true,  "is_bailable": false, "triable_by": "Court of Sessions" },
    "249": { "is_cognizable": true,  "is_bailable": true,  "triable_by": "Magistrate First Class" },
    "273": { "is_cognizable": true,  "is_bailable": false, "triable_by": "Court of Sessions" },
    "274": { "is_cognizable": true,  "is_bailable": false, "triable_by": "Court of Sessions" },
    "275": { "is_cognizable": true,  "is_bailable": false, "triable_by": "Court of Sessions" },
    "303": { "is_cognizable": true,  "is_bailable": true,  "triable_by": "Any Magistrate" },
    "304": { "is_cognizable": true,  "is_bailable": false, "triable_by": "Court of Sessions" },
    "305": { "is_cognizable": true,  "is_bailable": false, "triable_by": "Court of Sessions" },
    "308": { "is_cognizable": true,  "is_bailable": false, "triable_by": "Court of Sessions" },
    "309": { "is_cognizable": true,  "is_bailable": false, "triable_by": "Court of Sessions" },
    "310": { "is_cognizable": true,  "is_bailable": false, "triable_by": "Court of Sessions" },
    "316": { "is_cognizable": false, "is_bailable": true,  "triable_by": "Any Magistrate" },
    "318": { "is_cognizable": true,  "is_bailable": false, "triable_by": "Magistrate First Class" },
    "319": { "is_cognizable": true,  "is_bailable": false, "triable_by": "Court of Sessions" },
    "351": { "is_cognizable": true,  "is_bailable": false, "triable_by": "Magistrate First Class" },
    "352": { "is_cognizable": true,  "is_bailable": false, "triable_by": "Magistrate First Class" },
    "353": { "is_cognizable": true,  "is_bailable": false, "triable_by": "Magistrate First Class" },
    "63":  { "is_cognizable": true,  "is_bailable": false, "triable_by": "Court of Sessions" },
    "64":  { "is_cognizable": true,  "is_bailable": false, "triable_by": "Court of Sessions" },
    "65":  { "is_cognizable": true,  "is_bailable": false, "triable_by": "Court of Sessions" },
    "66":  { "is_cognizable": true,  "is_bailable": false, "triable_by": "Court of Sessions" },
    "67":  { "is_cognizable": true,  "is_bailable": false, "triable_by": "Court of Sessions" },
    "68":  { "is_cognizable": true,  "is_bailable": false, "triable_by": "Court of Sessions" },
    "70":  { "is_cognizable": true,  "is_bailable": false, "triable_by": "Court of Sessions" },
    "71":  { "is_cognizable": true,  "is_bailable": false, "triable_by": "Court of Sessions" },
    "72":  { "is_cognizable": true,  "is_bailable": false, "triable_by": "Court of Sessions" },
    "73":  { "is_cognizable": true,  "is_bailable": false, "triable_by": "Court of Sessions" },
    "74":  { "is_cognizable": true,  "is_bailable": false, "triable_by": "Court of Sessions" },
    "75":  { "is_cognizable": true,  "is_bailable": false, "triable_by": "Court of Sessions" },
    "76":  { "is_cognizable": true,  "is_bailable": false, "triable_by": "Court of Sessions" },
    "77":  { "is_cognizable": true,  "is_bailable": false, "triable_by": "Court of Sessions" },
    "78":  { "is_cognizable": true,  "is_bailable": false, "triable_by": "Court of Sessions" },
    "79":  { "is_cognizable": true,  "is_bailable": false, "triable_by": "Court of Sessions" },
    "80":  { "is_cognizable": true,  "is_bailable": false, "triable_by": "Court of Sessions" },
    "83":  { "is_cognizable": true,  "is_bailable": false, "triable_by": "Court of Sessions" },
    "84":  { "is_cognizable": true,  "is_bailable": false, "triable_by": "Magistrate First Class" },
    "85":  { "is_cognizable": true,  "is_bailable": false, "triable_by": "Magistrate First Class" },
    "86":  { "is_cognizable": true,  "is_bailable": false, "triable_by": "Magistrate First Class" },
    "87":  { "is_cognizable": true,  "is_bailable": false, "triable_by": "Court of Sessions" },
    "88":  { "is_cognizable": true,  "is_bailable": false, "triable_by": "Court of Sessions" },
    "89":  { "is_cognizable": true,  "is_bailable": false, "triable_by": "Court of Sessions" },
    "90":  { "is_cognizable": true,  "is_bailable": false, "triable_by": "Court of Sessions" },
    "91":  { "is_cognizable": true,  "is_bailable": false, "triable_by": "Court of Sessions" },
    "92":  { "is_cognizable": true,  "is_bailable": false, "triable_by": "Court of Sessions" },
    "93":  { "is_cognizable": true,  "is_bailable": false, "triable_by": "Court of Sessions" },
    "94":  { "is_cognizable": true,  "is_bailable": false, "triable_by": "Court of Sessions" },
    "95":  { "is_cognizable": true,  "is_bailable": false, "triable_by": "Court of Sessions" },
    "96":  { "is_cognizable": true,  "is_bailable": false, "triable_by": "Court of Sessions" }
  }
}
